{
  "name": "tiddlywiki",
  "slug": "tiddlywiki",
  "categories": [
    193
  ],
  "date_created": "2025-11-23",
  "interface_port": null,
  "documentation": "github.com/TiddlyWiki/TiddlyWiki5",
  "website": "tiddlywiki.com/",
  "source_code": "github.com/TiddlyWiki/TiddlyWiki5",
  "logo": "https://cdn.jsdelivr.net/gh/selfhst/icons/webp/tiddlywiki.webp",
  "description": "TiddlyWiki is a unique self-contained wiki and personal knowledge base that runs in the browser as a single HTML file. It supports plugins, scripting, and nonlinear note-taking, and can be self-hosted or stored locally.",
  "install_methods": [
    {
      "platform": {
        "desktop": {
          "linux": false,
          "windows": false,
          "macos": false
        },
        "mobile": {
          "android": false,
          "ios": false
        },
        "web_app": false,
        "browser_extension": false,
        "cli_only": false,
        "hosting": {
          "self_hosted": false,
          "saas": false,
          "managed_cloud": false
        },
        "ui": {
          "cli": false,
          "gui": false,
          "web_ui": false,
          "api": false,
          "tui": false
        }
      }
    }
  ],
  "default_credentials": {
    "username": null,
    "password": null
  },
  "notes": [],
  "platform": {
    "desktop": false,
    "mobile": false,
    "web_extensions": false,
    "hosting": false,
    "ui_interface": true
  },
  "deployment": {
    "script": true,
    "docker": true,
    "docker_compose": true,
    "helm": true,
    "kubernetes": true,
    "terraform": true,
    "paths": {
      "script": "/public/manifest/dummy/script.sh",
      "docker": "/public/manifest/dummy/Dockerfile",
      "docker_compose": "/public/manifest/dummy/docker-compose.yaml",
      "helm": "/public/manifest/dummy/helm.yaml",
      "kubernetes": "/public/manifest/dummy/k8s-deployment.yaml",
      "terraform": "/public/manifest/dummy/main.tf"
    }
  }
}